steam_market_history/__init__.py
steam_market_history/main.py
steam_market_history/modules/__init__.py
steam_market_history/modules/exporter.py
steam_market_history/modules/steam.py
steam_market_history/templates/index.html
steam_market_history-3.1.5.dist-info/METADATA
steam_market_history-3.1.5.dist-info/WHEEL
steam_market_history-3.1.5.dist-info/entry_points.txt
steam_market_history-3.1.5.dist-info/licenses/LICENSE
steam_market_history-3.1.5.dist-info/RECORD
