Metadata-Version: 2.4
Name: steam-market-history
Version: 3.1.5
Summary: An easy-to-use CLI to export your steam market history to various formats
License-Expression: MIT
License-File: LICENSE
Keywords: steam,cli,market,history,export
Author: Fabian Eulitz
Author-email: dev@sustineo.de
Requires-Python: >=3.10,<4.0
Classifier: Programming Language :: Python :: 3
Classifier: Programming Language :: Python :: 3.10
Classifier: Programming Language :: Python :: 3.11
Classifier: Programming Language :: Python :: 3.12
Classifier: Programming Language :: Python :: 3.13
Classifier: Programming Language :: Python :: 3.14
Requires-Dist: Jinja2 (>=3.1.6,<4.0.0)
Requires-Dist: beautifulsoup4 (>=4.14.3,<5.0.0)
Requires-Dist: steam-next (>=2.1.0,<3.0.0)
Requires-Dist: typer (>=0.21.0,<1.0.0)
Project-URL: repository, https://github.com/fabieu/steam-market-history
